pocketorm/__init__.py
pocketorm/models.py
pocketorm-0.3.0.dist-info/WHEEL
pocketorm-0.3.0.dist-info/METADATA
pocketorm-0.3.0.dist-info/RECORD
