Metadata-Version: 2.3
Name: pocketorm
Version: 0.3.0
Summary: Add your description here
Requires-Dist: peewee>=3.18.2
Requires-Python: >=3.12
